{"day":4,"date":"2026-06-30","metrics":["ele","speed","hr","cad","temp"],"movingS":12642,"pauseS":8233,"elapsedS":20875,"points":[{"d":0.038,"t":37,"gap":false,"ele":1388.81,"speed":2.5,"hr":78.67,"cad":52.67,"temp":21.0},{"d":0.083,"t":102,"gap":false,"ele":1388.74,"speed":3.13,"hr":91.28,"cad":66.11,"temp":21.0},{"d":0.175,"t":176,"gap":false,"ele":1390.28,"speed":4.61,"hr":88.28,"cad":54.94,"temp":21.0},{"d":0.261,"t":247,"gap":false,"ele":1391.88,"speed":4.53,"hr":81.78,"cad":76.61,"temp":20.22},{"d":0.343,"t":313,"gap":false,"ele":1393.21,"speed":4.5,"hr":87.11,"cad":95.39,"temp":20.0},{"d":0.422,"t":378,"gap":false,"ele":1395.31,"speed":4.41,"hr":91.33,"cad":91.22,"temp":19.28},{"d":0.493,"t":437,"gap":false,"ele":1396.62,"speed":4.19,"hr":89.17,"cad":83.0,"temp":19.83},{"d":0.548,"t":482,"gap":false,"ele":1398.33,"speed":4.04,"hr":94.33,"cad":63.0,"temp":20.0},{"d":0.618,"t":558,"gap":false,"ele":1398.71,"speed":2.14,"hr":91.11,"cad":44.28,"temp":20.0},{"d":0.717,"t":639,"gap":false,"ele":1399.61,"speed":4.38,"hr":92.56,"cad":89.44,"temp":20.0},{"d":0.802,"t":708,"gap":false,"ele":1400.82,"speed":4.38,"hr":97.89,"cad":96.44,"temp":20.39},{"d":0.859,"t":760,"gap":false,"ele":1405.4,"speed":3.35,"hr":105.0,"cad":70.17,"temp":21.0},{"d":0.921,"t":821,"gap":false,"ele":1413.73,"speed":0.72,"hr":118.11,"cad":13.94,"temp":21.0},{"d":0.959,"t":867,"gap":false,"ele":1419.2,"speed":0.07,"hr":123.0,"cad":15.28,"temp":21.33},{"d":0.975,"t":948,"gap":false,"ele":1418.9,"speed":0.27,"hr":110.72,"cad":0.0,"temp":21.94},{"d":0.998,"t":1021,"gap":false,"ele":1420.97,"speed":0.0,"hr":96.39,"cad":0.0,"temp":22.0},{"d":0.999,"t":1113,"gap":false,"ele":1420.72,"speed":0.79,"hr":86.06,"cad":11.11,"temp":22.0},{"d":1.06,"t":1162,"gap":false,"ele":1422.52,"speed":4.83,"hr":95.89,"cad":96.11,"temp":22.0},{"d":1.116,"t":1203,"gap":false,"ele":1427.83,"speed":4.68,"hr":106.94,"cad":51.06,"temp":22.22},{"d":1.177,"t":1257,"gap":false,"ele":1432.01,"speed":4.37,"hr":107.89,"cad":74.06,"temp":22.0},{"d":1.22,"t":1296,"gap":false,"ele":1435.9,"speed":4.19,"hr":105.39,"cad":62.17,"temp":22.0},{"d":1.284,"t":1358,"gap":false,"ele":1436.8,"speed":4.14,"hr":99.94,"cad":67.0,"temp":22.0},{"d":1.35,"t":1410,"gap":false,"ele":1430.81,"speed":4.46,"hr":90.17,"cad":69.5,"temp":22.0},{"d":1.419,"t":1471,"gap":false,"ele":1426.96,"speed":3.92,"hr":87.0,"cad":42.78,"temp":22.0},{"d":1.478,"t":1524,"gap":false,"ele":1426.88,"speed":3.98,"hr":85.78,"cad":93.39,"temp":22.83},{"d":1.545,"t":1582,"gap":false,"ele":1427.76,"speed":4.25,"hr":87.28,"cad":77.39,"temp":23.0},{"d":1.61,"t":1636,"gap":false,"ele":1429.33,"speed":4.22,"hr":94.5,"cad":70.56,"temp":22.5},{"d":1.676,"t":1693,"gap":false,"ele":1431.9,"speed":3.23,"hr":103.22,"cad":75.61,"temp":22.56},{"d":1.738,"t":1745,"gap":false,"ele":1433.08,"speed":4.29,"hr":99.72,"cad":58.56,"temp":22.72},{"d":1.833,"t":1823,"gap":false,"ele":1432.78,"speed":4.36,"hr":94.17,"cad":78.94,"temp":23.0},{"d":1.912,"t":1892,"gap":false,"ele":1434.82,"speed":4.15,"hr":95.67,"cad":82.17,"temp":23.0},{"d":1.99,"t":1957,"gap":false,"ele":1437.41,"speed":4.18,"hr":97.67,"cad":83.94,"temp":23.0},{"d":2.047,"t":2010,"gap":false,"ele":1441.81,"speed":3.89,"hr":103.94,"cad":85.5,"temp":23.0},{"d":2.105,"t":2062,"gap":false,"ele":1446.43,"speed":3.91,"hr":109.39,"cad":90.11,"temp":23.0},{"d":2.197,"t":2139,"gap":false,"ele":1448.23,"speed":4.22,"hr":100.44,"cad":56.17,"temp":23.28},{"d":2.258,"t":2198,"gap":false,"ele":1454.03,"speed":2.52,"hr":109.11,"cad":63.89,"temp":23.94},{"d":2.307,"t":2253,"gap":false,"ele":1462.6,"speed":3.04,"hr":116.44,"cad":54.28,"temp":23.89},{"d":2.35,"t":2300,"gap":false,"ele":1470.56,"speed":0.11,"hr":125.94,"cad":17.83,"temp":23.0},{"d":2.41,"t":2368,"gap":false,"ele":1478.93,"speed":0.0,"hr":121.78,"cad":0.0,"temp":23.0},{"d":2.473,"t":2434,"gap":false,"ele":1486.76,"speed":0.16,"hr":120.0,"cad":8.67,"temp":23.0},{"d":2.512,"t":2479,"gap":false,"ele":1492.46,"speed":0.48,"hr":126.56,"cad":8.67,"temp":23.0},{"d":2.569,"t":2536,"gap":false,"ele":1498.78,"speed":1.94,"hr":120.56,"cad":6.56,"temp":23.0},{"d":2.622,"t":2597,"gap":false,"ele":1506.88,"speed":0.15,"hr":122.22,"cad":11.67,"temp":23.0},{"d":2.686,"t":2671,"gap":false,"ele":1514.84,"speed":0.0,"hr":122.06,"cad":4.5,"temp":23.0},{"d":2.749,"t":2741,"gap":false,"ele":1522.13,"speed":0.37,"hr":113.72,"cad":25.94,"temp":23.89},{"d":2.789,"t":2785,"gap":false,"ele":1527.82,"speed":4.91,"hr":112.78,"cad":14.83,"temp":24.0},{"d":2.839,"t":2845,"gap":false,"ele":1534.68,"speed":2.8,"hr":115.56,"cad":18.94,"temp":24.0},{"d":2.881,"t":2898,"gap":false,"ele":1540.8,"speed":0.69,"hr":116.78,"cad":2.22,"temp":24.0},{"d":2.94,"t":2964,"gap":false,"ele":1547.09,"speed":2.35,"hr":111.89,"cad":20.0,"temp":24.5},{"d":2.99,"t":3027,"gap":false,"ele":1551.41,"speed":3.03,"hr":102.5,"cad":38.61,"temp":25.0},{"d":3.047,"t":3083,"gap":false,"ele":1556.7,"speed":1.97,"hr":102.17,"cad":29.0,"temp":25.0},{"d":3.087,"t":3130,"gap":false,"ele":1562.54,"speed":1.61,"hr":119.83,"cad":29.06,"temp":25.0},{"d":3.144,"t":3191,"gap":false,"ele":1568.58,"speed":3.79,"hr":118.56,"cad":45.44,"temp":25.0},{"d":3.184,"t":3261,"gap":false,"ele":1569.79,"speed":0.58,"hr":93.83,"cad":0.0,"temp":25.67},{"d":3.185,"t":3338,"gap":false,"ele":1570.69,"speed":0.0,"hr":73.83,"cad":0.0,"temp":26.0},{"d":3.187,"t":3431,"gap":false,"ele":1572.14,"speed":0.0,"hr":76.28,"cad":0.0,"temp":26.0},{"d":3.188,"t":3520,"gap":false,"ele":1573.76,"speed":0.0,"hr":71.06,"cad":0.0,"temp":25.83},{"d":3.188,"t":3619,"gap":false,"ele":1574.18,"speed":0.0,"hr":70.44,"cad":0.0,"temp":26.0},{"d":3.188,"t":3724,"gap":false,"ele":1575.09,"speed":0.0,"hr":71.39,"cad":0.0,"temp":26.22},{"d":3.188,"t":3814,"gap":false,"ele":1574.74,"speed":0.0,"hr":69.06,"cad":0.0,"temp":27.0},{"d":3.188,"t":3906,"gap":false,"ele":1575.47,"speed":0.0,"hr":74.11,"cad":0.0,"temp":27.33},{"d":3.221,"t":3980,"gap":false,"ele":1576.39,"speed":1.1,"hr":74.22,"cad":8.89,"temp":27.67},{"d":3.262,"t":4066,"gap":false,"ele":1576.66,"speed":3.38,"hr":75.78,"cad":82.83,"temp":26.61},{"d":3.312,"t":4115,"gap":false,"ele":1578.87,"speed":3.82,"hr":88.94,"cad":43.83,"temp":26.0},{"d":3.351,"t":4167,"gap":false,"ele":1584.69,"speed":0.05,"hr":103.72,"cad":0.0,"temp":25.67},{"d":3.401,"t":4231,"gap":false,"ele":1591.74,"speed":0.0,"hr":120.06,"cad":14.89,"temp":25.0},{"d":3.436,"t":4290,"gap":false,"ele":1597.81,"speed":0.0,"hr":112.78,"cad":0.0,"temp":25.0},{"d":3.487,"t":4357,"gap":false,"ele":1598.99,"speed":0.0,"hr":103.44,"cad":5.06,"temp":25.0},{"d":3.542,"t":4431,"gap":false,"ele":1603.19,"speed":0.3,"hr":109.33,"cad":20.17,"temp":24.78},{"d":3.592,"t":4509,"gap":false,"ele":1604.22,"speed":0.0,"hr":101.44,"cad":7.22,"temp":25.0},{"d":3.624,"t":4574,"gap":false,"ele":1606.29,"speed":0.0,"hr":94.39,"cad":3.78,"temp":24.83},{"d":3.666,"t":4646,"gap":false,"ele":1613.09,"speed":0.0,"hr":108.28,"cad":0.0,"temp":24.0},{"d":3.721,"t":4718,"gap":false,"ele":1616.9,"speed":0.1,"hr":104.83,"cad":8.61,"temp":24.0},{"d":3.765,"t":4780,"gap":false,"ele":1618.88,"speed":0.0,"hr":106.56,"cad":0.0,"temp":24.0},{"d":3.789,"t":4850,"gap":false,"ele":1619.42,"speed":0.0,"hr":94.78,"cad":9.5,"temp":24.0},{"d":3.822,"t":4923,"gap":false,"ele":1622.12,"speed":2.94,"hr":92.39,"cad":22.33,"temp":24.0},{"d":3.873,"t":4991,"gap":false,"ele":1629.21,"speed":0.0,"hr":114.67,"cad":4.61,"temp":24.0},{"d":3.91,"t":5050,"gap":false,"ele":1635.83,"speed":0.0,"hr":119.5,"cad":1.72,"temp":24.11},{"d":3.946,"t":5120,"gap":false,"ele":1640.96,"speed":0.0,"hr":114.17,"cad":1.72,"temp":24.72},{"d":3.95,"t":5204,"gap":false,"ele":1641.44,"speed":0.0,"hr":92.06,"cad":0.0,"temp":25.0},{"d":3.955,"t":5297,"gap":false,"ele":1641.97,"speed":0.78,"hr":70.5,"cad":8.83,"temp":25.5},{"d":4.007,"t":5348,"gap":false,"ele":1647.31,"speed":3.14,"hr":84.39,"cad":10.39,"temp":25.0},{"d":4.05,"t":5394,"gap":false,"ele":1652.28,"speed":1.18,"hr":87.78,"cad":34.44,"temp":24.11},{"d":4.094,"t":5452,"gap":false,"ele":1658.39,"speed":0.29,"hr":96.78,"cad":0.0,"temp":23.89},{"d":4.147,"t":5520,"gap":false,"ele":1666.14,"speed":0.0,"hr":105.17,"cad":18.83,"temp":23.94},{"d":4.196,"t":5583,"gap":false,"ele":1672.12,"speed":0.29,"hr":105.83,"cad":4.67,"temp":24.0},{"d":4.243,"t":5648,"gap":false,"ele":1679.18,"speed":0.0,"hr":109.72,"cad":0.0,"temp":24.0},{"d":4.263,"t":5711,"gap":false,"ele":1685.3,"speed":0.11,"hr":104.94,"cad":0.0,"temp":24.0},{"d":4.291,"t":5784,"gap":false,"ele":1692.34,"speed":1.13,"hr":105.11,"cad":46.72,"temp":23.44},{"d":4.318,"t":5839,"gap":false,"ele":1698.98,"speed":2.6,"hr":110.17,"cad":37.89,"temp":23.39},{"d":4.353,"t":5904,"gap":false,"ele":1708.01,"speed":0.0,"hr":111.06,"cad":1.78,"temp":23.33},{"d":4.388,"t":5964,"gap":false,"ele":1718.72,"speed":0.0,"hr":125.56,"cad":0.0,"temp":23.0},{"d":4.419,"t":6026,"gap":false,"ele":1727.24,"speed":2.47,"hr":121.56,"cad":73.06,"temp":23.0},{"d":4.449,"t":6077,"gap":false,"ele":1736.12,"speed":4.05,"hr":124.33,"cad":128.28,"temp":22.22},{"d":4.48,"t":6127,"gap":false,"ele":1744.73,"speed":2.75,"hr":126.0,"cad":67.5,"temp":22.0},{"d":4.509,"t":6181,"gap":false,"ele":1754.27,"speed":0.0,"hr":116.33,"cad":14.0,"temp":22.0},{"d":4.527,"t":6241,"gap":false,"ele":1760.56,"speed":0.0,"hr":101.17,"cad":0.0,"temp":22.0},{"d":4.535,"t":6305,"gap":false,"ele":1764.29,"speed":0.48,"hr":83.67,"cad":9.72,"temp":22.0},{"d":4.577,"t":6351,"gap":false,"ele":1772.97,"speed":0.05,"hr":98.89,"cad":11.28,"temp":22.0},{"d":4.608,"t":6411,"gap":false,"ele":1783.09,"speed":0.75,"hr":108.78,"cad":0.0,"temp":22.0},{"d":4.694,"t":6474,"gap":false,"ele":1787.04,"speed":0.56,"hr":98.33,"cad":0.0,"temp":21.39},{"d":4.719,"t":6526,"gap":false,"ele":1792.04,"speed":0.06,"hr":77.22,"cad":2.0,"temp":20.0},{"d":4.745,"t":6586,"gap":false,"ele":1796.67,"speed":0.0,"hr":90.61,"cad":0.0,"temp":19.11},{"d":4.752,"t":6658,"gap":false,"ele":1795.96,"speed":0.0,"hr":85.56,"cad":0.0,"temp":19.0},{"d":4.79,"t":6717,"gap":false,"ele":1788.76,"speed":0.68,"hr":78.0,"cad":34.56,"temp":19.33},{"d":4.822,"t":6770,"gap":false,"ele":1776.07,"speed":0.3,"hr":81.83,"cad":0.0,"temp":20.0},{"d":4.854,"t":6830,"gap":false,"ele":1767.38,"speed":0.0,"hr":81.83,"cad":0.0,"temp":20.0},{"d":4.879,"t":6890,"gap":false,"ele":1762.43,"speed":0.65,"hr":83.78,"cad":25.61,"temp":21.0},{"d":4.925,"t":6957,"gap":false,"ele":1752.23,"speed":0.0,"hr":77.5,"cad":5.61,"temp":22.0},{"d":4.952,"t":7012,"gap":false,"ele":1744.14,"speed":0.0,"hr":79.17,"cad":0.0,"temp":22.0},{"d":4.996,"t":7078,"gap":false,"ele":1733.09,"speed":0.27,"hr":82.61,"cad":9.67,"temp":22.0},{"d":5.034,"t":7134,"gap":false,"ele":1721.28,"speed":0.07,"hr":83.33,"cad":15.28,"temp":22.0},{"d":5.06,"t":7176,"gap":false,"ele":1711.91,"speed":0.47,"hr":83.06,"cad":35.56,"temp":22.72},{"d":5.103,"t":7233,"gap":false,"ele":1702.57,"speed":1.94,"hr":84.78,"cad":22.5,"temp":23.0},{"d":5.143,"t":7291,"gap":false,"ele":1694.24,"speed":2.14,"hr":81.94,"cad":22.5,"temp":23.78},{"d":5.188,"t":7356,"gap":false,"ele":1686.0,"speed":2.53,"hr":80.89,"cad":19.0,"temp":24.0},{"d":5.241,"t":7412,"gap":false,"ele":1677.68,"speed":3.86,"hr":75.28,"cad":0.0,"temp":24.0},{"d":5.277,"t":7472,"gap":false,"ele":1672.33,"speed":0.19,"hr":91.83,"cad":17.0,"temp":24.28},{"d":5.324,"t":7531,"gap":false,"ele":1664.91,"speed":2.92,"hr":87.17,"cad":35.28,"temp":25.0},{"d":5.375,"t":7582,"gap":false,"ele":1657.7,"speed":4.14,"hr":86.0,"cad":33.06,"temp":25.0},{"d":5.446,"t":7644,"gap":false,"ele":1651.87,"speed":4.06,"hr":80.33,"cad":43.44,"temp":25.0},{"d":5.467,"t":7721,"gap":false,"ele":1645.99,"speed":0.16,"hr":76.78,"cad":0.0,"temp":25.0},{"d":5.467,"t":7792,"gap":false,"ele":1644.44,"speed":0.0,"hr":75.22,"cad":0.0,"temp":24.33},{"d":5.469,"t":7888,"gap":false,"ele":1642.31,"speed":0.0,"hr":69.56,"cad":0.0,"temp":24.83},{"d":5.476,"t":7977,"gap":false,"ele":1641.51,"speed":0.0,"hr":69.28,"cad":0.0,"temp":25.28},{"d":5.479,"t":8082,"gap":false,"ele":1641.13,"speed":0.0,"hr":72.94,"cad":0.0,"temp":26.0},{"d":5.485,"t":8156,"gap":false,"ele":1640.34,"speed":0.28,"hr":72.5,"cad":25.5,"temp":26.0},{"d":5.52,"t":8220,"gap":false,"ele":1635.64,"speed":0.0,"hr":70.83,"cad":0.0,"temp":26.0},{"d":5.552,"t":8275,"gap":false,"ele":1630.52,"speed":0.0,"hr":74.17,"cad":8.06,"temp":25.06},{"d":5.629,"t":8342,"gap":false,"ele":1623.4,"speed":4.08,"hr":76.5,"cad":20.56,"temp":25.0},{"d":5.672,"t":8389,"gap":false,"ele":1620.57,"speed":2.91,"hr":72.67,"cad":13.83,"temp":25.0},{"d":5.729,"t":8458,"gap":false,"ele":1618.26,"speed":3.04,"hr":74.0,"cad":35.72,"temp":25.0},{"d":5.766,"t":8519,"gap":false,"ele":1613.09,"speed":0.18,"hr":70.89,"cad":0.0,"temp":25.0},{"d":5.79,"t":8603,"gap":false,"ele":1613.38,"speed":1.85,"hr":66.39,"cad":6.61,"temp":25.0},{"d":5.849,"t":8663,"gap":false,"ele":1611.14,"speed":3.87,"hr":68.33,"cad":15.06,"temp":25.0},{"d":5.896,"t":8720,"gap":false,"ele":1605.38,"speed":2.97,"hr":68.06,"cad":21.78,"temp":25.0},{"d":5.933,"t":8787,"gap":false,"ele":1603.7,"speed":0.0,"hr":74.06,"cad":8.28,"temp":25.0},{"d":5.966,"t":8863,"gap":false,"ele":1600.59,"speed":0.44,"hr":75.56,"cad":21.39,"temp":24.61},{"d":6.004,"t":8924,"gap":false,"ele":1594.51,"speed":0.59,"hr":75.06,"cad":8.5,"temp":24.17},{"d":6.041,"t":8980,"gap":false,"ele":1588.73,"speed":0.0,"hr":80.56,"cad":17.0,"temp":24.0},{"d":6.103,"t":9047,"gap":false,"ele":1582.81,"speed":3.35,"hr":75.83,"cad":39.61,"temp":24.0},{"d":6.157,"t":9113,"gap":false,"ele":1582.94,"speed":2.31,"hr":83.72,"cad":14.0,"temp":24.17},{"d":6.191,"t":9176,"gap":false,"ele":1581.68,"speed":0.0,"hr":89.39,"cad":9.11,"temp":25.0},{"d":6.193,"t":9267,"gap":false,"ele":1580.13,"speed":0.0,"hr":73.5,"cad":0.0,"temp":25.83},{"d":6.193,"t":9358,"gap":false,"ele":1578.88,"speed":0.0,"hr":74.11,"cad":0.0,"temp":26.0},{"d":6.193,"t":9441,"gap":false,"ele":1577.68,"speed":0.0,"hr":70.06,"cad":0.0,"temp":25.22},{"d":6.199,"t":9521,"gap":false,"ele":1576.88,"speed":0.0,"hr":68.89,"cad":0.0,"temp":25.0},{"d":6.205,"t":9594,"gap":false,"ele":1575.31,"speed":0.0,"hr":68.61,"cad":0.0,"temp":26.0},{"d":6.206,"t":9695,"gap":false,"ele":1575.12,"speed":0.0,"hr":69.5,"cad":0.0,"temp":25.17},{"d":6.212,"t":9772,"gap":false,"ele":1575.26,"speed":0.0,"hr":74.39,"cad":0.0,"temp":25.0},{"d":6.217,"t":9864,"gap":false,"ele":1576.03,"speed":0.0,"hr":79.78,"cad":0.0,"temp":25.0},{"d":6.235,"t":9951,"gap":false,"ele":1576.21,"speed":0.0,"hr":76.78,"cad":0.0,"temp":24.83},{"d":6.238,"t":10024,"gap":false,"ele":1576.51,"speed":0.0,"hr":66.89,"cad":0.0,"temp":24.72},{"d":6.249,"t":10098,"gap":false,"ele":1576.16,"speed":0.0,"hr":75.17,"cad":0.0,"temp":25.0},{"d":6.25,"t":10186,"gap":false,"ele":1577.03,"speed":0.0,"hr":61.44,"cad":0.0,"temp":25.0},{"d":6.262,"t":10266,"gap":false,"ele":1577.46,"speed":0.0,"hr":61.5,"cad":0.0,"temp":24.61},{"d":6.267,"t":10346,"gap":false,"ele":1577.77,"speed":0.0,"hr":62.89,"cad":0.0,"temp":24.0},{"d":6.337,"t":10422,"gap":false,"ele":1577.29,"speed":0.18,"hr":56.5,"cad":0.0,"temp":24.67},{"d":6.392,"t":10492,"gap":false,"ele":1578.01,"speed":0.08,"hr":56.72,"cad":0.0,"temp":25.0},{"d":6.416,"t":10564,"gap":false,"ele":1579.72,"speed":1.56,"hr":60.83,"cad":22.67,"temp":25.0},{"d":6.474,"t":10620,"gap":false,"ele":1582.21,"speed":4.53,"hr":74.28,"cad":25.44,"temp":25.0},{"d":6.522,"t":10677,"gap":false,"ele":1587.7,"speed":1.83,"hr":74.72,"cad":4.83,"temp":25.0},{"d":6.564,"t":10738,"gap":false,"ele":1594.96,"speed":0.0,"hr":87.0,"cad":0.0,"temp":25.0},{"d":6.608,"t":10794,"gap":false,"ele":1600.66,"speed":0.0,"hr":99.06,"cad":0.0,"temp":25.0},{"d":6.652,"t":10853,"gap":false,"ele":1606.24,"speed":0.0,"hr":94.06,"cad":0.0,"temp":25.0},{"d":6.68,"t":10925,"gap":false,"ele":1611.48,"speed":0.0,"hr":98.61,"cad":3.67,"temp":26.06},{"d":6.715,"t":10991,"gap":false,"ele":1617.9,"speed":0.0,"hr":96.67,"cad":0.0,"temp":27.0},{"d":6.759,"t":11043,"gap":false,"ele":1616.73,"speed":0.29,"hr":81.83,"cad":10.72,"temp":27.0},{"d":6.832,"t":11107,"gap":false,"ele":1614.32,"speed":4.61,"hr":73.39,"cad":9.0,"temp":27.0},{"d":6.855,"t":11167,"gap":false,"ele":1616.32,"speed":0.47,"hr":95.11,"cad":12.72,"temp":27.0},{"d":6.907,"t":11222,"gap":false,"ele":1621.27,"speed":4.34,"hr":112.78,"cad":21.44,"temp":26.67},{"d":6.954,"t":11281,"gap":false,"ele":1628.28,"speed":0.72,"hr":121.89,"cad":0.0,"temp":26.0},{"d":7.015,"t":11342,"gap":false,"ele":1634.97,"speed":1.42,"hr":122.17,"cad":52.39,"temp":25.83},{"d":7.054,"t":11379,"gap":false,"ele":1639.14,"speed":3.24,"hr":114.06,"cad":30.89,"temp":25.0},{"d":7.083,"t":11448,"gap":false,"ele":1642.98,"speed":2.4,"hr":109.06,"cad":35.89,"temp":25.0},{"d":7.118,"t":11499,"gap":false,"ele":1650.22,"speed":0.32,"hr":118.78,"cad":14.61,"temp":25.0},{"d":7.159,"t":11552,"gap":false,"ele":1654.83,"speed":0.21,"hr":118.5,"cad":0.0,"temp":25.83},{"d":7.201,"t":11608,"gap":false,"ele":1661.38,"speed":0.0,"hr":124.67,"cad":7.44,"temp":26.0},{"d":7.228,"t":11668,"gap":false,"ele":1667.27,"speed":0.64,"hr":120.89,"cad":30.17,"temp":26.0},{"d":7.271,"t":11727,"gap":false,"ele":1674.92,"speed":4.18,"hr":124.94,"cad":0.0,"temp":26.0},{"d":7.313,"t":11784,"gap":false,"ele":1682.08,"speed":3.27,"hr":124.22,"cad":17.0,"temp":26.0},{"d":7.351,"t":11840,"gap":false,"ele":1689.51,"speed":2.54,"hr":126.5,"cad":9.67,"temp":26.0},{"d":7.403,"t":11905,"gap":false,"ele":1696.43,"speed":0.0,"hr":122.06,"cad":14.11,"temp":25.17},{"d":7.444,"t":11969,"gap":false,"ele":1704.3,"speed":0.16,"hr":123.61,"cad":4.5,"temp":25.0},{"d":7.488,"t":12037,"gap":false,"ele":1708.22,"speed":0.73,"hr":117.11,"cad":0.0,"temp":25.72},{"d":7.537,"t":12105,"gap":false,"ele":1710.47,"speed":1.48,"hr":101.89,"cad":26.83,"temp":26.0},{"d":7.56,"t":12178,"gap":false,"ele":1712.09,"speed":0.32,"hr":91.0,"cad":19.11,"temp":26.0},{"d":7.612,"t":12254,"gap":false,"ele":1716.06,"speed":0.64,"hr":92.22,"cad":29.06,"temp":25.33},{"d":7.669,"t":12310,"gap":false,"ele":1716.81,"speed":4.19,"hr":104.56,"cad":25.67,"temp":25.0},{"d":7.725,"t":12365,"gap":false,"ele":1709.94,"speed":4.49,"hr":93.89,"cad":21.89,"temp":25.72},{"d":7.774,"t":12416,"gap":false,"ele":1707.44,"speed":4.07,"hr":92.72,"cad":17.33,"temp":26.0},{"d":7.833,"t":12472,"gap":false,"ele":1707.43,"speed":4.11,"hr":88.83,"cad":27.89,"temp":25.5},{"d":7.888,"t":12526,"gap":false,"ele":1710.06,"speed":3.81,"hr":88.72,"cad":20.39,"temp":25.0},{"d":7.945,"t":12575,"gap":false,"ele":1708.52,"speed":4.03,"hr":98.94,"cad":16.94,"temp":24.83},{"d":8.016,"t":12635,"gap":false,"ele":1704.83,"speed":4.17,"hr":94.89,"cad":46.22,"temp":24.56},{"d":8.054,"t":12678,"gap":false,"ele":1705.0,"speed":0.25,"hr":94.11,"cad":0.0,"temp":25.0},{"d":8.089,"t":12758,"gap":false,"ele":1705.37,"speed":0.0,"hr":85.56,"cad":0.0,"temp":25.11},{"d":8.135,"t":12833,"gap":false,"ele":1705.6,"speed":0.0,"hr":81.06,"cad":0.0,"temp":26.17},{"d":8.156,"t":12918,"gap":false,"ele":1706.3,"speed":0.0,"hr":80.39,"cad":0.0,"temp":26.0},{"d":8.16,"t":13025,"gap":false,"ele":1706.36,"speed":0.0,"hr":80.33,"cad":0.0,"temp":26.28},{"d":8.206,"t":13104,"gap":false,"ele":1705.97,"speed":3.51,"hr":77.17,"cad":41.56,"temp":27.0},{"d":8.269,"t":13161,"gap":false,"ele":1706.81,"speed":4.39,"hr":82.61,"cad":11.0,"temp":27.0},{"d":8.337,"t":13226,"gap":false,"ele":1703.5,"speed":2.47,"hr":87.33,"cad":34.11,"temp":26.94},{"d":8.392,"t":13285,"gap":false,"ele":1703.22,"speed":3.5,"hr":87.78,"cad":58.33,"temp":26.61},{"d":8.431,"t":13331,"gap":false,"ele":1705.02,"speed":0.58,"hr":92.89,"cad":4.94,"temp":26.06},{"d":8.465,"t":13393,"gap":false,"ele":1705.9,"speed":2.08,"hr":82.56,"cad":52.67,"temp":26.0},{"d":8.519,"t":13439,"gap":false,"ele":1708.21,"speed":2.57,"hr":87.78,"cad":30.5,"temp":26.0},{"d":8.59,"t":13507,"gap":false,"ele":1710.51,"speed":1.73,"hr":98.5,"cad":14.94,"temp":26.0},{"d":8.621,"t":13538,"gap":false,"ele":1714.29,"speed":1.56,"hr":105.17,"cad":0.0,"temp":26.0},{"d":8.663,"t":13585,"gap":false,"ele":1717.66,"speed":2.85,"hr":106.17,"cad":42.28,"temp":26.0},{"d":8.7,"t":13634,"gap":false,"ele":1722.49,"speed":0.95,"hr":106.11,"cad":17.56,"temp":26.0},{"d":8.746,"t":13685,"gap":false,"ele":1728.66,"speed":0.12,"hr":116.83,"cad":9.11,"temp":26.0},{"d":8.815,"t":13754,"gap":false,"ele":1732.69,"speed":2.38,"hr":111.67,"cad":25.94,"temp":26.0},{"d":8.865,"t":13824,"gap":false,"ele":1739.71,"speed":0.0,"hr":114.78,"cad":0.0,"temp":26.0},{"d":8.89,"t":13895,"gap":false,"ele":1744.97,"speed":0.0,"hr":117.28,"cad":3.67,"temp":26.0},{"d":8.934,"t":13963,"gap":false,"ele":1749.42,"speed":1.24,"hr":118.44,"cad":0.0,"temp":26.0},{"d":8.981,"t":14044,"gap":false,"ele":1751.09,"speed":0.0,"hr":108.0,"cad":0.0,"temp":26.0},{"d":9.005,"t":14135,"gap":false,"ele":1750.09,"speed":1.38,"hr":94.56,"cad":37.17,"temp":26.56},{"d":9.033,"t":14217,"gap":false,"ele":1748.61,"speed":0.0,"hr":86.54,"cad":0.0,"temp":27.22},{"d":9.035,"t":14303,"gap":false,"ele":1750.03,"speed":0.0,"hr":71.0,"cad":0.0,"temp":25.72},{"d":9.036,"t":14398,"gap":false,"ele":1751.98,"speed":0.0,"hr":83.0,"cad":0.0,"temp":24.17},{"d":9.044,"t":14466,"gap":false,"ele":1751.26,"speed":0.0,"hr":93.28,"cad":17.0,"temp":24.94},{"d":9.066,"t":14550,"gap":false,"ele":1750.37,"speed":0.54,"hr":94.17,"cad":16.5,"temp":25.5},{"d":9.07,"t":14629,"gap":false,"ele":1749.28,"speed":0.0,"hr":97.78,"cad":6.39,"temp":26.5},{"d":9.093,"t":14702,"gap":false,"ele":1748.24,"speed":0.08,"hr":96.33,"cad":18.67,"temp":27.33},{"d":9.095,"t":14781,"gap":false,"ele":1747.23,"speed":0.86,"hr":101.17,"cad":35.83,"temp":28.94},{"d":9.118,"t":14849,"gap":false,"ele":1746.44,"speed":0.0,"hr":89.28,"cad":0.0,"temp":30.0},{"d":9.12,"t":14947,"gap":false,"ele":1746.77,"speed":0.0,"hr":86.33,"cad":0.0,"temp":30.89},{"d":9.12,"t":15040,"gap":false,"ele":1746.43,"speed":0.0,"hr":86.83,"cad":0.0,"temp":32.0},{"d":9.141,"t":15124,"gap":false,"ele":1746.7,"speed":1.27,"hr":81.17,"cad":32.67,"temp":32.0},{"d":9.197,"t":15203,"gap":false,"ele":1747.04,"speed":0.42,"hr":81.89,"cad":32.94,"temp":32.0},{"d":9.199,"t":15299,"gap":false,"ele":1747.56,"speed":0.32,"hr":81.67,"cad":0.0,"temp":32.06},{"d":9.22,"t":15384,"gap":false,"ele":1747.37,"speed":0.09,"hr":76.94,"cad":7.89,"temp":32.78},{"d":9.246,"t":15454,"gap":false,"ele":1747.71,"speed":0.49,"hr":83.33,"cad":33.39,"temp":33.0},{"d":9.277,"t":15508,"gap":false,"ele":1747.89,"speed":0.41,"hr":93.83,"cad":4.67,"temp":33.0},{"d":9.299,"t":15595,"gap":false,"ele":1747.94,"speed":2.06,"hr":84.56,"cad":21.83,"temp":33.0},{"d":9.328,"t":15681,"gap":false,"ele":1748.47,"speed":0.0,"hr":88.39,"cad":0.0,"temp":33.0},{"d":9.342,"t":15745,"gap":false,"ele":1748.91,"speed":0.76,"hr":94.17,"cad":43.78,"temp":33.0},{"d":9.388,"t":15826,"gap":false,"ele":1748.59,"speed":1.81,"hr":94.11,"cad":25.78,"temp":33.72},{"d":9.398,"t":15903,"gap":false,"ele":1748.3,"speed":0.06,"hr":87.28,"cad":11.94,"temp":34.0},{"d":9.429,"t":15992,"gap":false,"ele":1748.86,"speed":0.0,"hr":93.5,"cad":0.0,"temp":34.0},{"d":9.453,"t":16081,"gap":false,"ele":1749.01,"speed":0.08,"hr":93.5,"cad":12.89,"temp":34.0},{"d":9.478,"t":16145,"gap":false,"ele":1749.44,"speed":0.1,"hr":94.67,"cad":10.94,"temp":33.89},{"d":9.487,"t":16224,"gap":false,"ele":1750.14,"speed":0.0,"hr":98.33,"cad":0.0,"temp":33.0},{"d":9.49,"t":16305,"gap":false,"ele":1750.36,"speed":0.0,"hr":84.0,"cad":4.94,"temp":32.44},{"d":9.499,"t":16403,"gap":false,"ele":1749.58,"speed":0.0,"hr":88.78,"cad":5.06,"temp":32.83},{"d":9.511,"t":16481,"gap":false,"ele":1748.91,"speed":0.69,"hr":90.67,"cad":25.56,"temp":33.78},{"d":9.529,"t":16545,"gap":false,"ele":1749.23,"speed":0.3,"hr":91.72,"cad":17.0,"temp":34.0},{"d":9.552,"t":16631,"gap":false,"ele":1748.84,"speed":0.0,"hr":88.17,"cad":5.89,"temp":34.72},{"d":9.573,"t":16693,"gap":false,"ele":1749.06,"speed":0.06,"hr":86.44,"cad":9.0,"temp":35.0},{"d":9.583,"t":16777,"gap":false,"ele":1749.44,"speed":0.24,"hr":89.89,"cad":9.17,"temp":35.0},{"d":9.592,"t":16863,"gap":false,"ele":1750.18,"speed":0.0,"hr":88.89,"cad":5.06,"temp":34.11},{"d":9.613,"t":16943,"gap":false,"ele":1750.24,"speed":0.0,"hr":90.44,"cad":0.0,"temp":35.0},{"d":9.616,"t":17038,"gap":false,"ele":1751.1,"speed":0.0,"hr":89.33,"cad":17.72,"temp":35.0},{"d":9.638,"t":17108,"gap":false,"ele":1751.58,"speed":4.14,"hr":93.5,"cad":48.06,"temp":35.0},{"d":9.677,"t":17168,"gap":false,"ele":1752.02,"speed":1.17,"hr":88.94,"cad":7.33,"temp":34.33},{"d":9.677,"t":17263,"gap":false,"ele":1752.5,"speed":0.0,"hr":80.94,"cad":0.0,"temp":33.5},{"d":9.68,"t":17355,"gap":false,"ele":1752.63,"speed":0.0,"hr":81.39,"cad":0.0,"temp":33.0},{"d":9.687,"t":17420,"gap":false,"ele":1752.17,"speed":0.87,"hr":88.22,"cad":27.83,"temp":32.72},{"d":9.754,"t":17488,"gap":false,"ele":1748.78,"speed":3.52,"hr":86.61,"cad":15.67,"temp":32.0},{"d":9.797,"t":17548,"gap":false,"ele":1746.12,"speed":0.77,"hr":85.06,"cad":7.0,"temp":31.67},{"d":9.842,"t":17615,"gap":false,"ele":1745.91,"speed":3.52,"hr":89.5,"cad":21.39,"temp":31.0},{"d":9.888,"t":17665,"gap":false,"ele":1749.33,"speed":4.16,"hr":107.17,"cad":5.06,"temp":31.39},{"d":9.935,"t":17714,"gap":false,"ele":1753.84,"speed":2.11,"hr":112.17,"cad":4.83,"temp":32.0},{"d":9.988,"t":17782,"gap":false,"ele":1761.54,"speed":0.06,"hr":116.28,"cad":5.78,"temp":32.0},{"d":10.03,"t":17842,"gap":false,"ele":1770.02,"speed":0.07,"hr":119.78,"cad":5.28,"temp":32.44},{"d":10.05,"t":17908,"gap":false,"ele":1776.32,"speed":0.07,"hr":130.28,"cad":0.0,"temp":33.56},{"d":10.1,"t":17982,"gap":false,"ele":1781.31,"speed":2.65,"hr":124.11,"cad":37.72,"temp":34.94},{"d":10.144,"t":18039,"gap":false,"ele":1786.63,"speed":0.9,"hr":121.39,"cad":25.28,"temp":34.0},{"d":10.198,"t":18102,"gap":false,"ele":1796.27,"speed":0.16,"hr":133.0,"cad":3.89,"temp":33.33},{"d":10.247,"t":18167,"gap":false,"ele":1805.66,"speed":0.0,"hr":137.0,"cad":0.0,"temp":33.0},{"d":10.293,"t":18228,"gap":false,"ele":1816.11,"speed":0.0,"hr":140.78,"cad":5.44,"temp":32.17},{"d":10.333,"t":18294,"gap":false,"ele":1826.56,"speed":0.92,"hr":140.44,"cad":35.39,"temp":31.61},{"d":10.391,"t":18360,"gap":false,"ele":1835.39,"speed":4.25,"hr":142.17,"cad":0.0,"temp":31.0},{"d":10.437,"t":18416,"gap":false,"ele":1840.78,"speed":3.93,"hr":137.44,"cad":14.17,"temp":31.0},{"d":10.5,"t":18482,"gap":false,"ele":1846.86,"speed":3.54,"hr":135.61,"cad":0.0,"temp":30.33},{"d":10.559,"t":18542,"gap":false,"ele":1853.54,"speed":3.8,"hr":134.94,"cad":57.39,"temp":30.0},{"d":10.604,"t":18588,"gap":false,"ele":1858.63,"speed":2.8,"hr":135.61,"cad":18.83,"temp":30.0},{"d":10.643,"t":18663,"gap":false,"ele":1862.36,"speed":1.28,"hr":124.0,"cad":0.0,"temp":30.44},{"d":10.643,"t":18737,"gap":false,"ele":1862.13,"speed":0.0,"hr":100.28,"cad":0.0,"temp":31.11},{"d":10.644,"t":18825,"gap":false,"ele":1862.23,"speed":0.0,"hr":93.83,"cad":0.0,"temp":31.72},{"d":10.659,"t":18895,"gap":false,"ele":1862.99,"speed":0.43,"hr":94.94,"cad":20.56,"temp":32.0},{"d":10.705,"t":18943,"gap":false,"ele":1867.89,"speed":0.24,"hr":104.39,"cad":2.17,"temp":31.33},{"d":10.735,"t":18997,"gap":false,"ele":1873.31,"speed":1.75,"hr":118.44,"cad":22.33,"temp":31.0},{"d":10.802,"t":19066,"gap":false,"ele":1879.58,"speed":3.79,"hr":128.89,"cad":23.11,"temp":31.44},{"d":10.849,"t":19114,"gap":false,"ele":1884.49,"speed":3.78,"hr":126.89,"cad":4.5,"temp":32.78},{"d":10.895,"t":19164,"gap":false,"ele":1890.54,"speed":3.56,"hr":124.0,"cad":6.0,"temp":33.5},{"d":10.942,"t":19215,"gap":false,"ele":1896.58,"speed":1.31,"hr":122.89,"cad":4.11,"temp":34.0},{"d":10.986,"t":19267,"gap":false,"ele":1903.96,"speed":0.0,"hr":128.06,"cad":0.0,"temp":34.67},{"d":11.032,"t":19324,"gap":false,"ele":1910.92,"speed":0.0,"hr":132.28,"cad":0.0,"temp":35.0},{"d":11.069,"t":19382,"gap":false,"ele":1918.54,"speed":0.0,"hr":136.33,"cad":23.56,"temp":35.56},{"d":11.115,"t":19443,"gap":false,"ele":1928.07,"speed":0.0,"hr":130.06,"cad":5.78,"temp":35.0},{"d":11.147,"t":19496,"gap":false,"ele":1937.24,"speed":0.0,"hr":131.44,"cad":0.0,"temp":35.0},{"d":11.178,"t":19552,"gap":false,"ele":1945.11,"speed":0.0,"hr":148.06,"cad":0.0,"temp":35.44},{"d":11.211,"t":19617,"gap":false,"ele":1955.39,"speed":0.0,"hr":151.78,"cad":0.0,"temp":35.44},{"d":11.262,"t":19685,"gap":false,"ele":1965.08,"speed":0.4,"hr":148.67,"cad":20.5,"temp":35.0},{"d":11.274,"t":19755,"gap":false,"ele":1969.6,"speed":0.0,"hr":133.78,"cad":0.0,"temp":33.83},{"d":11.276,"t":19832,"gap":false,"ele":1971.54,"speed":0.0,"hr":107.22,"cad":0.0,"temp":32.5},{"d":11.28,"t":19931,"gap":false,"ele":1971.42,"speed":0.0,"hr":95.61,"cad":11.83,"temp":32.33},{"d":11.28,"t":20035,"gap":false,"ele":1971.03,"speed":0.0,"hr":91.22,"cad":0.0,"temp":32.72},{"d":11.28,"t":20133,"gap":false,"ele":1970.89,"speed":0.0,"hr":88.39,"cad":0.0,"temp":33.0},{"d":11.28,"t":20206,"gap":false,"ele":1971.04,"speed":0.0,"hr":87.89,"cad":0.0,"temp":33.0},{"d":11.28,"t":20294,"gap":false,"ele":1970.57,"speed":0.0,"hr":83.72,"cad":5.67,"temp":33.11},{"d":11.28,"t":20386,"gap":false,"ele":1972.34,"speed":0.0,"hr":86.94,"cad":20.11,"temp":33.0},{"d":11.31,"t":20434,"gap":false,"ele":1978.77,"speed":0.27,"hr":109.39,"cad":0.0,"temp":33.0},{"d":11.354,"t":20498,"gap":false,"ele":1986.17,"speed":0.0,"hr":112.72,"cad":0.0,"temp":33.0},{"d":11.382,"t":20541,"gap":false,"ele":1992.91,"speed":0.0,"hr":115.94,"cad":1.78,"temp":33.0},{"d":11.422,"t":20604,"gap":false,"ele":2001.4,"speed":0.0,"hr":115.28,"cad":0.0,"temp":33.0},{"d":11.455,"t":20657,"gap":false,"ele":2009.31,"speed":0.0,"hr":105.44,"cad":4.83,"temp":33.0},{"d":11.51,"t":20721,"gap":false,"ele":2016.9,"speed":2.24,"hr":105.06,"cad":25.78,"temp":33.0},{"d":11.548,"t":20775,"gap":false,"ele":2021.73,"speed":0.06,"hr":123.28,"cad":11.28,"temp":33.0},{"d":11.597,"t":20847,"gap":false,"ele":2021.85,"speed":0.93,"hr":116.41,"cad":9.0,"temp":33.0}]}