{"day":6,"date":"2026-07-02","metrics":["ele","speed","hr","cad","temp"],"movingS":22391,"pauseS":14173,"elapsedS":36564,"points":[{"d":0.049,"t":38,"gap":false,"ele":1227.35,"speed":3.37,"hr":81.35,"cad":78.03,"temp":26.87},{"d":0.155,"t":126,"gap":false,"ele":1226.82,"speed":4.26,"hr":91.97,"cad":64.9,"temp":28.61},{"d":0.268,"t":222,"gap":false,"ele":1233.44,"speed":4.15,"hr":96.13,"cad":87.1,"temp":28.61},{"d":0.366,"t":315,"gap":false,"ele":1240.15,"speed":4.11,"hr":100.29,"cad":69.71,"temp":28.0},{"d":0.486,"t":404,"gap":false,"ele":1247.34,"speed":3.79,"hr":103.29,"cad":50.19,"temp":27.94},{"d":0.592,"t":490,"gap":false,"ele":1253.01,"speed":3.81,"hr":102.35,"cad":76.94,"temp":27.42},{"d":0.708,"t":591,"gap":false,"ele":1261.54,"speed":4.73,"hr":115.03,"cad":79.23,"temp":28.29},{"d":0.788,"t":667,"gap":false,"ele":1270.74,"speed":2.9,"hr":125.97,"cad":48.23,"temp":29.0},{"d":0.876,"t":749,"gap":false,"ele":1278.54,"speed":3.3,"hr":116.32,"cad":66.23,"temp":29.0},{"d":0.957,"t":837,"gap":false,"ele":1291.52,"speed":3.46,"hr":125.81,"cad":4.58,"temp":28.87},{"d":1.041,"t":936,"gap":false,"ele":1306.72,"speed":2.54,"hr":127.71,"cad":24.1,"temp":28.52},{"d":1.134,"t":1048,"gap":false,"ele":1320.89,"speed":1.61,"hr":123.13,"cad":49.68,"temp":28.26},{"d":1.211,"t":1145,"gap":false,"ele":1335.19,"speed":1.26,"hr":129.13,"cad":57.68,"temp":27.29},{"d":1.304,"t":1258,"gap":false,"ele":1347.08,"speed":3.35,"hr":122.26,"cad":63.58,"temp":27.0},{"d":1.41,"t":1363,"gap":false,"ele":1352.97,"speed":3.65,"hr":112.35,"cad":37.16,"temp":27.0},{"d":1.501,"t":1453,"gap":false,"ele":1362.91,"speed":1.38,"hr":125.1,"cad":14.13,"temp":26.1},{"d":1.591,"t":1560,"gap":false,"ele":1376.22,"speed":0.76,"hr":129.74,"cad":47.48,"temp":27.13},{"d":1.71,"t":1668,"gap":false,"ele":1385.18,"speed":5.02,"hr":112.48,"cad":84.55,"temp":26.94},{"d":1.841,"t":1780,"gap":false,"ele":1377.68,"speed":4.44,"hr":94.84,"cad":48.39,"temp":26.58},{"d":1.958,"t":1882,"gap":false,"ele":1379.23,"speed":3.74,"hr":108.97,"cad":79.52,"temp":28.0},{"d":2.081,"t":1988,"gap":false,"ele":1386.13,"speed":3.88,"hr":103.77,"cad":76.94,"temp":27.35},{"d":2.206,"t":2093,"gap":false,"ele":1393.25,"speed":3.95,"hr":110.68,"cad":69.39,"temp":27.9},{"d":2.308,"t":2181,"gap":false,"ele":1391.79,"speed":4.36,"hr":107.26,"cad":56.48,"temp":29.55},{"d":2.415,"t":2273,"gap":false,"ele":1396.85,"speed":3.55,"hr":110.68,"cad":77.65,"temp":29.26},{"d":2.518,"t":2365,"gap":false,"ele":1401.33,"speed":4.34,"hr":105.9,"cad":90.19,"temp":28.58},{"d":2.65,"t":2473,"gap":false,"ele":1400.91,"speed":4.47,"hr":97.68,"cad":47.16,"temp":28.81},{"d":2.794,"t":2590,"gap":false,"ele":1391.31,"speed":4.47,"hr":91.68,"cad":75.61,"temp":28.58},{"d":2.909,"t":2683,"gap":false,"ele":1389.34,"speed":4.16,"hr":98.68,"cad":85.52,"temp":28.71},{"d":3.019,"t":2776,"gap":false,"ele":1397.65,"speed":4.05,"hr":109.39,"cad":79.19,"temp":29.0},{"d":3.129,"t":2869,"gap":false,"ele":1406.79,"speed":4.47,"hr":114.52,"cad":82.26,"temp":29.0},{"d":3.264,"t":2980,"gap":false,"ele":1415.7,"speed":4.32,"hr":116.19,"cad":81.55,"temp":29.06},{"d":3.382,"t":3077,"gap":false,"ele":1425.37,"speed":4.38,"hr":112.74,"cad":92.48,"temp":28.23},{"d":3.521,"t":3187,"gap":false,"ele":1433.39,"speed":4.51,"hr":111.39,"cad":89.81,"temp":29.0},{"d":3.658,"t":3295,"gap":false,"ele":1441.34,"speed":4.58,"hr":114.42,"cad":88.77,"temp":29.74},{"d":3.797,"t":3411,"gap":false,"ele":1453.89,"speed":4.36,"hr":117.13,"cad":85.23,"temp":29.61},{"d":3.885,"t":3516,"gap":false,"ele":1461.57,"speed":2.8,"hr":114.23,"cad":49.26,"temp":27.74},{"d":3.976,"t":3624,"gap":false,"ele":1466.63,"speed":1.72,"hr":104.77,"cad":7.74,"temp":27.48},{"d":3.991,"t":3746,"gap":false,"ele":1467.33,"speed":0.0,"hr":74.23,"cad":3.06,"temp":26.45},{"d":4.015,"t":3883,"gap":false,"ele":1469.12,"speed":0.0,"hr":80.9,"cad":0.0,"temp":25.06},{"d":4.017,"t":4026,"gap":false,"ele":1469.52,"speed":0.0,"hr":66.32,"cad":0.0,"temp":24.39},{"d":4.037,"t":4185,"gap":false,"ele":1470.23,"speed":0.0,"hr":67.77,"cad":10.84,"temp":24.03},{"d":4.098,"t":4287,"gap":false,"ele":1473.82,"speed":2.84,"hr":80.35,"cad":26.68,"temp":24.97},{"d":4.175,"t":4373,"gap":false,"ele":1478.01,"speed":2.96,"hr":101.71,"cad":7.26,"temp":25.45},{"d":4.253,"t":4470,"gap":false,"ele":1482.79,"speed":0.0,"hr":111.84,"cad":8.77,"temp":25.9},{"d":4.305,"t":4590,"gap":false,"ele":1484.46,"speed":0.0,"hr":93.65,"cad":0.0,"temp":26.58},{"d":4.321,"t":4717,"gap":false,"ele":1486.1,"speed":1.87,"hr":71.26,"cad":24.68,"temp":25.39},{"d":4.408,"t":4806,"gap":false,"ele":1493.57,"speed":3.73,"hr":90.13,"cad":63.84,"temp":25.0},{"d":4.499,"t":4898,"gap":false,"ele":1502.97,"speed":3.85,"hr":94.94,"cad":84.06,"temp":24.0},{"d":4.594,"t":4990,"gap":false,"ele":1510.63,"speed":3.69,"hr":107.1,"cad":67.29,"temp":24.0},{"d":4.724,"t":5111,"gap":false,"ele":1514.3,"speed":3.12,"hr":109.16,"cad":72.23,"temp":24.94},{"d":4.833,"t":5218,"gap":false,"ele":1525.05,"speed":3.66,"hr":119.97,"cad":69.32,"temp":25.0},{"d":4.925,"t":5334,"gap":false,"ele":1532.39,"speed":1.39,"hr":101.55,"cad":28.45,"temp":25.45},{"d":4.98,"t":5412,"gap":false,"ele":1540.15,"speed":0.57,"hr":108.74,"cad":28.52,"temp":25.29},{"d":5.081,"t":5530,"gap":false,"ele":1554.59,"speed":2.44,"hr":126.58,"cad":47.1,"temp":26.0},{"d":5.168,"t":5645,"gap":false,"ele":1569.35,"speed":3.17,"hr":129.13,"cad":13.26,"temp":25.29},{"d":5.241,"t":5752,"gap":false,"ele":1582.51,"speed":2.47,"hr":128.32,"cad":4.35,"temp":25.0},{"d":5.325,"t":5870,"gap":false,"ele":1596.37,"speed":2.46,"hr":130.42,"cad":35.48,"temp":25.0},{"d":5.404,"t":5979,"gap":false,"ele":1611.63,"speed":0.17,"hr":129.77,"cad":6.0,"temp":25.0},{"d":5.48,"t":6095,"gap":false,"ele":1624.76,"speed":1.03,"hr":126.55,"cad":27.94,"temp":25.0},{"d":5.561,"t":6202,"gap":false,"ele":1637.06,"speed":2.18,"hr":125.16,"cad":24.74,"temp":25.0},{"d":5.6,"t":6311,"gap":false,"ele":1643.26,"speed":0.0,"hr":109.03,"cad":0.0,"temp":25.71},{"d":5.624,"t":6407,"gap":false,"ele":1646.69,"speed":0.66,"hr":95.71,"cad":24.9,"temp":25.0},{"d":5.733,"t":6520,"gap":false,"ele":1657.14,"speed":3.96,"hr":113.52,"cad":37.94,"temp":25.0},{"d":5.841,"t":6628,"gap":false,"ele":1666.06,"speed":2.91,"hr":112.97,"cad":43.23,"temp":25.39},{"d":5.947,"t":6729,"gap":false,"ele":1675.68,"speed":3.92,"hr":119.23,"cad":53.65,"temp":26.0},{"d":6.053,"t":6835,"gap":false,"ele":1688.13,"speed":3.45,"hr":121.77,"cad":8.26,"temp":26.0},{"d":6.155,"t":6950,"gap":false,"ele":1700.19,"speed":1.62,"hr":122.1,"cad":40.55,"temp":26.0},{"d":6.258,"t":7070,"gap":false,"ele":1712.34,"speed":3.72,"hr":122.16,"cad":31.26,"temp":26.23},{"d":6.359,"t":7185,"gap":false,"ele":1725.15,"speed":2.98,"hr":123.58,"cad":49.74,"temp":26.65},{"d":6.478,"t":7300,"gap":false,"ele":1735.28,"speed":3.4,"hr":118.68,"cad":66.1,"temp":27.0},{"d":6.618,"t":7423,"gap":false,"ele":1743.39,"speed":3.62,"hr":112.26,"cad":57.52,"temp":27.0},{"d":6.701,"t":7523,"gap":false,"ele":1752.57,"speed":0.0,"hr":112.97,"cad":6.81,"temp":26.55},{"d":6.712,"t":7659,"gap":false,"ele":1753.26,"speed":0.0,"hr":82.94,"cad":6.97,"temp":26.45},{"d":6.714,"t":7799,"gap":false,"ele":1753.98,"speed":0.0,"hr":81.35,"cad":4.16,"temp":26.48},{"d":6.75,"t":7920,"gap":false,"ele":1753.92,"speed":0.14,"hr":93.23,"cad":5.74,"temp":28.35},{"d":6.818,"t":8013,"gap":false,"ele":1760.66,"speed":0.0,"hr":99.26,"cad":4.26,"temp":29.0},{"d":6.893,"t":8109,"gap":false,"ele":1769.63,"speed":2.28,"hr":115.06,"cad":21.32,"temp":29.0},{"d":6.959,"t":8216,"gap":false,"ele":1782.21,"speed":0.39,"hr":124.42,"cad":7.68,"temp":29.42},{"d":7.03,"t":8318,"gap":false,"ele":1794.35,"speed":0.0,"hr":125.29,"cad":12.13,"temp":29.42},{"d":7.103,"t":8427,"gap":false,"ele":1801.51,"speed":0.31,"hr":115.26,"cad":21.77,"temp":29.97},{"d":7.155,"t":8520,"gap":false,"ele":1813.16,"speed":0.24,"hr":122.71,"cad":4.94,"temp":29.42},{"d":7.224,"t":8616,"gap":false,"ele":1829.08,"speed":2.04,"hr":134.74,"cad":44.65,"temp":29.03},{"d":7.269,"t":8721,"gap":false,"ele":1842.41,"speed":0.06,"hr":117.1,"cad":19.87,"temp":27.68},{"d":7.342,"t":8815,"gap":false,"ele":1857.35,"speed":1.29,"hr":132.26,"cad":35.39,"temp":27.52},{"d":7.41,"t":8928,"gap":false,"ele":1872.26,"speed":0.04,"hr":128.71,"cad":4.68,"temp":27.0},{"d":7.46,"t":9029,"gap":false,"ele":1886.52,"speed":0.41,"hr":131.97,"cad":12.19,"temp":27.0},{"d":7.539,"t":9149,"gap":false,"ele":1895.91,"speed":1.42,"hr":123.68,"cad":29.03,"temp":27.9},{"d":7.632,"t":9255,"gap":false,"ele":1901.04,"speed":4.34,"hr":118.97,"cad":24.61,"temp":29.1},{"d":7.713,"t":9355,"gap":false,"ele":1907.43,"speed":1.65,"hr":117.45,"cad":10.16,"temp":29.68},{"d":7.729,"t":9466,"gap":false,"ele":1911.21,"speed":0.0,"hr":90.58,"cad":0.0,"temp":27.68},{"d":7.745,"t":9595,"gap":false,"ele":1910.61,"speed":0.0,"hr":78.84,"cad":0.0,"temp":26.1},{"d":7.756,"t":9733,"gap":false,"ele":1909.66,"speed":0.0,"hr":73.39,"cad":0.0,"temp":25.13},{"d":7.779,"t":9852,"gap":false,"ele":1909.37,"speed":0.0,"hr":76.48,"cad":0.0,"temp":24.32},{"d":7.782,"t":10019,"gap":false,"ele":1907.86,"speed":0.0,"hr":75.03,"cad":0.0,"temp":22.58},{"d":7.783,"t":10172,"gap":false,"ele":1903.83,"speed":0.0,"hr":67.94,"cad":0.0,"temp":24.39},{"d":7.784,"t":10331,"gap":false,"ele":1902.81,"speed":0.0,"hr":67.81,"cad":0.0,"temp":24.65},{"d":7.784,"t":10506,"gap":false,"ele":1902.42,"speed":0.0,"hr":63.23,"cad":0.0,"temp":25.13},{"d":7.784,"t":10639,"gap":false,"ele":1901.86,"speed":0.0,"hr":79.1,"cad":6.97,"temp":25.0},{"d":7.838,"t":10738,"gap":false,"ele":1895.75,"speed":3.23,"hr":67.19,"cad":22.48,"temp":25.48},{"d":7.942,"t":10835,"gap":false,"ele":1895.75,"speed":4.02,"hr":73.87,"cad":29.84,"temp":27.45},{"d":8.07,"t":10953,"gap":false,"ele":1893.55,"speed":3.35,"hr":68.58,"cad":32.68,"temp":29.0},{"d":8.161,"t":11050,"gap":false,"ele":1897.05,"speed":1.27,"hr":68.0,"cad":22.32,"temp":29.74},{"d":8.233,"t":11159,"gap":false,"ele":1906.83,"speed":0.0,"hr":98.58,"cad":13.87,"temp":30.0},{"d":8.294,"t":11255,"gap":false,"ele":1918.15,"speed":0.08,"hr":120.71,"cad":9.35,"temp":29.06},{"d":8.383,"t":11357,"gap":false,"ele":1923.23,"speed":4.14,"hr":106.9,"cad":34.55,"temp":29.26},{"d":8.468,"t":11466,"gap":false,"ele":1929.46,"speed":2.96,"hr":104.68,"cad":25.0,"temp":29.55},{"d":8.527,"t":11548,"gap":false,"ele":1942.1,"speed":1.02,"hr":119.65,"cad":21.74,"temp":28.1},{"d":8.586,"t":11640,"gap":false,"ele":1954.39,"speed":0.72,"hr":126.77,"cad":0.0,"temp":26.74},{"d":8.699,"t":11748,"gap":false,"ele":1957.02,"speed":4.16,"hr":115.16,"cad":53.45,"temp":26.97},{"d":8.774,"t":11822,"gap":false,"ele":1960.61,"speed":1.71,"hr":113.58,"cad":5.87,"temp":27.0},{"d":8.864,"t":11915,"gap":false,"ele":1965.42,"speed":2.36,"hr":121.55,"cad":34.84,"temp":27.0},{"d":8.969,"t":12017,"gap":false,"ele":1960.21,"speed":2.74,"hr":106.81,"cad":41.03,"temp":27.77},{"d":9.073,"t":12125,"gap":false,"ele":1963.15,"speed":0.38,"hr":109.06,"cad":16.94,"temp":27.61},{"d":9.144,"t":12220,"gap":false,"ele":1969.29,"speed":2.15,"hr":119.32,"cad":17.61,"temp":26.39},{"d":9.231,"t":12301,"gap":false,"ele":1977.16,"speed":2.28,"hr":121.32,"cad":32.84,"temp":26.52},{"d":9.277,"t":12391,"gap":false,"ele":1992.32,"speed":0.07,"hr":140.71,"cad":3.84,"temp":26.32},{"d":9.338,"t":12503,"gap":false,"ele":2006.85,"speed":0.0,"hr":138.52,"cad":4.16,"temp":25.68},{"d":9.402,"t":12613,"gap":false,"ele":2013.57,"speed":1.17,"hr":116.0,"cad":19.29,"temp":27.23},{"d":9.42,"t":12734,"gap":false,"ele":2012.26,"speed":0.12,"hr":87.48,"cad":4.81,"temp":29.06},{"d":9.421,"t":12876,"gap":false,"ele":2011.17,"speed":0.0,"hr":82.26,"cad":8.13,"temp":29.71},{"d":9.467,"t":13014,"gap":false,"ele":2014.94,"speed":1.84,"hr":96.81,"cad":7.81,"temp":29.0},{"d":9.567,"t":13124,"gap":false,"ele":2023.77,"speed":3.62,"hr":113.81,"cad":36.77,"temp":29.0},{"d":9.66,"t":13222,"gap":false,"ele":2030.86,"speed":3.66,"hr":114.19,"cad":46.03,"temp":29.16},{"d":9.715,"t":13300,"gap":false,"ele":2043.4,"speed":0.26,"hr":115.45,"cad":14.97,"temp":28.58},{"d":9.793,"t":13393,"gap":false,"ele":2053.33,"speed":2.05,"hr":120.19,"cad":22.45,"temp":28.0},{"d":9.866,"t":13489,"gap":false,"ele":2063.96,"speed":1.14,"hr":132.9,"cad":30.45,"temp":27.48},{"d":9.943,"t":13594,"gap":false,"ele":2070.15,"speed":2.35,"hr":128.84,"cad":51.55,"temp":27.29},{"d":10.067,"t":13705,"gap":false,"ele":2072.79,"speed":4.29,"hr":116.45,"cad":45.9,"temp":28.19},{"d":10.19,"t":13817,"gap":false,"ele":2080.75,"speed":3.05,"hr":125.03,"cad":32.0,"temp":28.0},{"d":10.268,"t":13912,"gap":false,"ele":2092.85,"speed":0.04,"hr":130.48,"cad":23.42,"temp":27.9},{"d":10.359,"t":14026,"gap":false,"ele":2101.45,"speed":2.48,"hr":123.16,"cad":27.65,"temp":27.23},{"d":10.375,"t":14169,"gap":false,"ele":2100.6,"speed":0.0,"hr":90.65,"cad":0.0,"temp":28.71},{"d":10.378,"t":14329,"gap":false,"ele":2098.1,"speed":0.0,"hr":79.87,"cad":0.0,"temp":30.45},{"d":10.378,"t":14463,"gap":false,"ele":2098.08,"speed":0.0,"hr":90.65,"cad":0.0,"temp":31.55},{"d":10.418,"t":14601,"gap":false,"ele":2103.49,"speed":0.37,"hr":96.0,"cad":22.61,"temp":31.0},{"d":10.465,"t":14709,"gap":false,"ele":2114.36,"speed":0.67,"hr":119.23,"cad":5.55,"temp":31.0},{"d":10.577,"t":14821,"gap":false,"ele":2118.06,"speed":5.02,"hr":111.1,"cad":14.35,"temp":31.0},{"d":10.677,"t":14923,"gap":false,"ele":2123.71,"speed":3.63,"hr":119.84,"cad":17.77,"temp":30.35},{"d":10.771,"t":15022,"gap":false,"ele":2132.43,"speed":1.5,"hr":123.77,"cad":25.71,"temp":29.23},{"d":10.859,"t":15122,"gap":false,"ele":2143.6,"speed":2.89,"hr":129.35,"cad":46.77,"temp":28.48},{"d":10.903,"t":15236,"gap":false,"ele":2148.05,"speed":0.09,"hr":106.9,"cad":0.0,"temp":28.0},{"d":10.929,"t":15388,"gap":false,"ele":2147.57,"speed":0.64,"hr":101.29,"cad":25.9,"temp":28.0},{"d":11.02,"t":15483,"gap":false,"ele":2147.52,"speed":0.99,"hr":103.84,"cad":16.16,"temp":27.9},{"d":11.047,"t":15610,"gap":false,"ele":2146.08,"speed":0.07,"hr":93.68,"cad":3.06,"temp":28.13},{"d":11.099,"t":15728,"gap":false,"ele":2146.19,"speed":0.0,"hr":72.19,"cad":0.0,"temp":27.81},{"d":11.177,"t":15844,"gap":false,"ele":2145.92,"speed":0.0,"hr":67.06,"cad":0.0,"temp":27.39},{"d":11.264,"t":15952,"gap":false,"ele":2145.67,"speed":0.0,"hr":65.45,"cad":0.0,"temp":27.97},{"d":11.313,"t":16067,"gap":false,"ele":2145.91,"speed":0.06,"hr":70.23,"cad":0.0,"temp":27.65},{"d":11.38,"t":16192,"gap":false,"ele":2144.78,"speed":0.05,"hr":69.03,"cad":5.06,"temp":28.0},{"d":11.472,"t":16308,"gap":false,"ele":2144.49,"speed":0.07,"hr":79.65,"cad":0.0,"temp":28.0},{"d":11.527,"t":16446,"gap":false,"ele":2144.66,"speed":0.0,"hr":74.03,"cad":0.0,"temp":28.0},{"d":11.57,"t":16578,"gap":false,"ele":2144.66,"speed":0.0,"hr":73.58,"cad":0.0,"temp":27.68},{"d":11.613,"t":16687,"gap":false,"ele":2144.81,"speed":0.0,"hr":74.61,"cad":0.0,"temp":27.32},{"d":11.684,"t":16812,"gap":false,"ele":2143.92,"speed":0.0,"hr":70.32,"cad":0.0,"temp":28.0},{"d":11.782,"t":16945,"gap":false,"ele":2144.08,"speed":0.2,"hr":77.39,"cad":5.03,"temp":28.0},{"d":11.812,"t":17079,"gap":false,"ele":2145.86,"speed":0.0,"hr":69.48,"cad":0.0,"temp":28.0},{"d":11.846,"t":17222,"gap":false,"ele":2146.7,"speed":0.0,"hr":68.03,"cad":0.0,"temp":27.84},{"d":11.888,"t":17367,"gap":false,"ele":2146.49,"speed":0.0,"hr":67.61,"cad":0.0,"temp":27.0},{"d":11.908,"t":17512,"gap":false,"ele":2145.96,"speed":0.04,"hr":65.52,"cad":0.0,"temp":27.0},{"d":11.977,"t":17637,"gap":false,"ele":2146.13,"speed":0.0,"hr":76.03,"cad":0.0,"temp":26.94},{"d":11.999,"t":17772,"gap":false,"ele":2147.28,"speed":0.0,"hr":81.45,"cad":0.0,"temp":26.26},{"d":12.004,"t":17885,"gap":false,"ele":2143.68,"speed":0.0,"hr":74.9,"cad":3.61,"temp":29.48},{"d":12.036,"t":18000,"gap":false,"ele":2143.69,"speed":0.16,"hr":80.61,"cad":2.61,"temp":30.71},{"d":12.09,"t":18125,"gap":false,"ele":2145.83,"speed":0.0,"hr":74.94,"cad":0.0,"temp":29.58},{"d":12.156,"t":18250,"gap":false,"ele":2146.79,"speed":0.04,"hr":74.35,"cad":0.0,"temp":29.16},{"d":12.286,"t":18358,"gap":false,"ele":2148.94,"speed":0.5,"hr":71.87,"cad":0.0,"temp":27.06},{"d":12.347,"t":18453,"gap":false,"ele":2149.85,"speed":0.0,"hr":72.78,"cad":0.0,"temp":24.29},{"d":12.385,"t":18562,"gap":false,"ele":2146.79,"speed":0.0,"hr":84.45,"cad":7.1,"temp":25.74},{"d":12.56,"t":18705,"gap":false,"ele":2147.77,"speed":0.08,"hr":82.29,"cad":13.55,"temp":26.0},{"d":12.614,"t":18812,"gap":false,"ele":2146.19,"speed":0.04,"hr":86.74,"cad":12.48,"temp":26.48},{"d":12.636,"t":18958,"gap":false,"ele":2143.84,"speed":1.72,"hr":86.55,"cad":55.03,"temp":27.29},{"d":12.684,"t":19047,"gap":false,"ele":2144.64,"speed":0.77,"hr":95.9,"cad":32.06,"temp":28.29},{"d":12.719,"t":19181,"gap":false,"ele":2141.41,"speed":0.11,"hr":81.87,"cad":8.52,"temp":29.68},{"d":12.8,"t":19320,"gap":false,"ele":2145.34,"speed":0.08,"hr":87.32,"cad":0.0,"temp":28.26},{"d":12.857,"t":19426,"gap":false,"ele":2145.05,"speed":1.0,"hr":93.48,"cad":21.26,"temp":28.48},{"d":12.919,"t":19553,"gap":false,"ele":2143.99,"speed":0.0,"hr":82.68,"cad":0.0,"temp":29.0},{"d":12.951,"t":19682,"gap":false,"ele":2145.51,"speed":0.78,"hr":85.71,"cad":20.45,"temp":28.87},{"d":12.964,"t":19827,"gap":false,"ele":2146.34,"speed":1.2,"hr":86.52,"cad":19.29,"temp":27.68},{"d":13.021,"t":19924,"gap":false,"ele":2144.19,"speed":1.11,"hr":82.23,"cad":4.68,"temp":29.26},{"d":13.024,"t":20071,"gap":false,"ele":2144.52,"speed":0.0,"hr":78.48,"cad":0.0,"temp":29.0},{"d":13.046,"t":20222,"gap":false,"ele":2144.81,"speed":2.12,"hr":82.71,"cad":25.55,"temp":29.29},{"d":13.146,"t":20318,"gap":false,"ele":2149.94,"speed":2.82,"hr":104.03,"cad":27.48,"temp":30.42},{"d":13.209,"t":20427,"gap":false,"ele":2160.67,"speed":0.0,"hr":123.19,"cad":3.9,"temp":31.0},{"d":13.238,"t":20520,"gap":false,"ele":2169.28,"speed":0.0,"hr":119.55,"cad":0.0,"temp":29.06},{"d":13.277,"t":20628,"gap":false,"ele":2165.23,"speed":3.58,"hr":102.71,"cad":20.32,"temp":27.13},{"d":13.364,"t":20730,"gap":false,"ele":2156.41,"speed":1.03,"hr":109.32,"cad":17.23,"temp":27.55},{"d":13.432,"t":20830,"gap":false,"ele":2158.92,"speed":0.03,"hr":122.9,"cad":2.61,"temp":28.1},{"d":13.471,"t":20960,"gap":false,"ele":2158.77,"speed":0.44,"hr":88.94,"cad":0.0,"temp":28.0},{"d":13.516,"t":21058,"gap":false,"ele":2160.47,"speed":1.1,"hr":94.55,"cad":3.13,"temp":27.68},{"d":13.564,"t":21216,"gap":false,"ele":2158.41,"speed":2.03,"hr":89.48,"cad":40.74,"temp":27.32},{"d":13.626,"t":21303,"gap":false,"ele":2163.95,"speed":0.35,"hr":106.26,"cad":13.26,"temp":26.0},{"d":13.652,"t":21406,"gap":false,"ele":2168.69,"speed":1.85,"hr":106.42,"cad":22.26,"temp":26.29},{"d":13.721,"t":21501,"gap":false,"ele":2171.9,"speed":0.61,"hr":97.94,"cad":8.9,"temp":27.23},{"d":13.737,"t":21630,"gap":false,"ele":2176.04,"speed":0.44,"hr":101.77,"cad":14.45,"temp":28.19},{"d":13.826,"t":21740,"gap":false,"ele":2184.82,"speed":2.61,"hr":121.65,"cad":1.23,"temp":28.0},{"d":13.897,"t":21843,"gap":false,"ele":2198.32,"speed":0.49,"hr":126.45,"cad":18.16,"temp":28.0},{"d":13.966,"t":21952,"gap":false,"ele":2201.19,"speed":1.76,"hr":95.16,"cad":16.48,"temp":27.13},{"d":14.063,"t":22070,"gap":false,"ele":2203.79,"speed":2.22,"hr":90.19,"cad":42.9,"temp":27.48},{"d":14.135,"t":22149,"gap":false,"ele":2210.77,"speed":3.26,"hr":107.9,"cad":38.03,"temp":26.06},{"d":14.219,"t":22252,"gap":false,"ele":2221.6,"speed":2.96,"hr":115.16,"cad":34.74,"temp":26.0},{"d":14.328,"t":22364,"gap":false,"ele":2229.57,"speed":1.3,"hr":131.35,"cad":21.81,"temp":26.0},{"d":14.419,"t":22478,"gap":false,"ele":2240.27,"speed":2.96,"hr":139.42,"cad":8.58,"temp":26.45},{"d":14.462,"t":22600,"gap":false,"ele":2245.83,"speed":0.0,"hr":107.39,"cad":0.0,"temp":26.03},{"d":14.501,"t":22748,"gap":false,"ele":2246.74,"speed":1.94,"hr":94.87,"cad":18.19,"temp":27.77},{"d":14.567,"t":22826,"gap":false,"ele":2257.54,"speed":0.0,"hr":128.1,"cad":9.71,"temp":27.29},{"d":14.622,"t":22939,"gap":false,"ele":2265.0,"speed":2.27,"hr":126.84,"cad":20.97,"temp":27.97},{"d":14.75,"t":23063,"gap":false,"ele":2268.8,"speed":3.32,"hr":119.32,"cad":16.13,"temp":28.35},{"d":14.848,"t":23180,"gap":false,"ele":2276.74,"speed":0.0,"hr":134.1,"cad":0.0,"temp":29.16},{"d":14.928,"t":23285,"gap":false,"ele":2290.83,"speed":3.1,"hr":136.94,"cad":22.26,"temp":30.0},{"d":15.008,"t":23397,"gap":false,"ele":2304.46,"speed":0.04,"hr":135.0,"cad":16.26,"temp":29.68},{"d":15.069,"t":23506,"gap":false,"ele":2318.13,"speed":0.0,"hr":135.55,"cad":0.0,"temp":29.81},{"d":15.098,"t":23619,"gap":false,"ele":2327.09,"speed":0.0,"hr":110.74,"cad":0.0,"temp":29.0},{"d":15.103,"t":23776,"gap":false,"ele":2329.39,"speed":0.0,"hr":91.23,"cad":2.94,"temp":29.77},{"d":15.103,"t":23880,"gap":false,"ele":2341.77,"speed":0.3,"hr":128.87,"cad":0.0,"temp":30.03},{"d":15.201,"t":24006,"gap":false,"ele":2354.9,"speed":0.0,"hr":132.84,"cad":0.0,"temp":30.0},{"d":15.205,"t":24147,"gap":false,"ele":2369.88,"speed":0.0,"hr":131.42,"cad":6.61,"temp":30.0},{"d":15.206,"t":24278,"gap":false,"ele":2378.68,"speed":0.0,"hr":120.23,"cad":4.58,"temp":30.0},{"d":15.206,"t":24403,"gap":false,"ele":2384.92,"speed":0.34,"hr":101.94,"cad":0.0,"temp":28.94},{"d":15.276,"t":24484,"gap":false,"ele":2396.85,"speed":0.0,"hr":134.1,"cad":0.0,"temp":28.0},{"d":15.331,"t":24603,"gap":false,"ele":2412.86,"speed":0.27,"hr":138.48,"cad":2.52,"temp":28.13},{"d":15.369,"t":24719,"gap":false,"ele":2423.31,"speed":0.55,"hr":119.35,"cad":0.0,"temp":28.13},{"d":15.375,"t":24827,"gap":false,"ele":2435.14,"speed":0.0,"hr":130.71,"cad":0.0,"temp":28.0},{"d":15.427,"t":24956,"gap":false,"ele":2450.86,"speed":0.75,"hr":139.32,"cad":0.0,"temp":28.81},{"d":15.465,"t":25071,"gap":false,"ele":2460.47,"speed":0.77,"hr":120.97,"cad":8.52,"temp":29.32},{"d":15.468,"t":25198,"gap":false,"ele":2462.86,"speed":0.0,"hr":98.84,"cad":0.0,"temp":27.26},{"d":15.468,"t":25343,"gap":false,"ele":2460.81,"speed":0.0,"hr":87.74,"cad":0.0,"temp":27.19},{"d":15.469,"t":25498,"gap":false,"ele":2462.52,"speed":0.0,"hr":90.58,"cad":11.03,"temp":25.71},{"d":15.469,"t":25611,"gap":false,"ele":2457.86,"speed":0.0,"hr":87.77,"cad":3.81,"temp":28.13},{"d":15.481,"t":25738,"gap":false,"ele":2454.04,"speed":0.25,"hr":93.29,"cad":18.13,"temp":28.32},{"d":15.539,"t":25819,"gap":false,"ele":2448.5,"speed":2.57,"hr":95.9,"cad":67.16,"temp":28.87},{"d":15.567,"t":25882,"gap":false,"ele":2461.63,"speed":0.15,"hr":122.55,"cad":24.61,"temp":27.03},{"d":15.586,"t":25993,"gap":false,"ele":2461.56,"speed":0.26,"hr":111.42,"cad":5.68,"temp":26.39},{"d":15.588,"t":26143,"gap":false,"ele":2456.2,"speed":0.0,"hr":91.58,"cad":13.77,"temp":27.23},{"d":15.625,"t":26246,"gap":false,"ele":2440.45,"speed":1.67,"hr":92.03,"cad":17.61,"temp":28.68},{"d":15.68,"t":26369,"gap":false,"ele":2431.2,"speed":0.79,"hr":91.32,"cad":34.19,"temp":27.1},{"d":15.756,"t":26471,"gap":false,"ele":2418.26,"speed":3.38,"hr":90.94,"cad":13.13,"temp":26.58},{"d":15.804,"t":26542,"gap":false,"ele":2406.18,"speed":2.91,"hr":93.9,"cad":18.61,"temp":27.87},{"d":15.868,"t":26658,"gap":false,"ele":2407.45,"speed":1.05,"hr":102.48,"cad":9.35,"temp":26.55},{"d":15.928,"t":26767,"gap":false,"ele":2394.12,"speed":1.44,"hr":90.42,"cad":35.26,"temp":26.0},{"d":16.014,"t":26862,"gap":false,"ele":2375.96,"speed":3.44,"hr":80.32,"cad":38.26,"temp":26.55},{"d":16.062,"t":26948,"gap":false,"ele":2364.04,"speed":1.97,"hr":88.84,"cad":44.48,"temp":27.9},{"d":16.146,"t":27037,"gap":false,"ele":2352.01,"speed":3.24,"hr":97.13,"cad":11.71,"temp":29.1},{"d":16.188,"t":27143,"gap":false,"ele":2344.25,"speed":0.54,"hr":111.32,"cad":3.13,"temp":30.26},{"d":16.314,"t":27279,"gap":false,"ele":2338.3,"speed":3.24,"hr":111.29,"cad":16.39,"temp":30.06},{"d":16.396,"t":27400,"gap":false,"ele":2338.46,"speed":1.15,"hr":117.68,"cad":20.45,"temp":27.52},{"d":16.479,"t":27505,"gap":false,"ele":2324.25,"speed":1.84,"hr":106.68,"cad":38.77,"temp":27.1},{"d":16.547,"t":27593,"gap":false,"ele":2311.08,"speed":0.08,"hr":124.29,"cad":26.74,"temp":27.61},{"d":16.6,"t":27692,"gap":false,"ele":2296.41,"speed":0.08,"hr":107.94,"cad":2.45,"temp":27.0},{"d":16.664,"t":27795,"gap":false,"ele":2290.25,"speed":0.0,"hr":109.1,"cad":3.23,"temp":28.58},{"d":16.689,"t":27915,"gap":false,"ele":2293.23,"speed":0.5,"hr":93.52,"cad":7.1,"temp":29.0},{"d":16.774,"t":28004,"gap":false,"ele":2296.86,"speed":1.13,"hr":110.55,"cad":25.39,"temp":29.35},{"d":16.869,"t":28122,"gap":false,"ele":2293.35,"speed":3.64,"hr":101.16,"cad":5.42,"temp":29.35},{"d":16.936,"t":28217,"gap":false,"ele":2286.46,"speed":0.07,"hr":109.13,"cad":7.94,"temp":30.13},{"d":17.0,"t":28325,"gap":false,"ele":2293.3,"speed":0.36,"hr":123.16,"cad":6.68,"temp":29.1},{"d":17.086,"t":28429,"gap":false,"ele":2289.8,"speed":0.7,"hr":109.26,"cad":5.1,"temp":28.0},{"d":17.113,"t":28572,"gap":false,"ele":2292.53,"speed":0.0,"hr":102.61,"cad":5.84,"temp":28.0},{"d":17.149,"t":28715,"gap":false,"ele":2293.89,"speed":0.0,"hr":102.06,"cad":0.0,"temp":28.74},{"d":17.182,"t":28836,"gap":false,"ele":2297.05,"speed":0.22,"hr":114.23,"cad":0.0,"temp":30.0},{"d":17.235,"t":28973,"gap":false,"ele":2303.07,"speed":0.2,"hr":133.45,"cad":8.97,"temp":29.65},{"d":17.289,"t":29075,"gap":false,"ele":2309.42,"speed":0.68,"hr":132.0,"cad":0.0,"temp":30.13},{"d":17.343,"t":29191,"gap":false,"ele":2315.46,"speed":1.12,"hr":127.13,"cad":5.68,"temp":31.13},{"d":17.404,"t":29305,"gap":false,"ele":2316.63,"speed":2.52,"hr":121.0,"cad":6.58,"temp":29.61},{"d":17.479,"t":29398,"gap":false,"ele":2304.02,"speed":2.83,"hr":111.74,"cad":35.29,"temp":29.0},{"d":17.51,"t":29529,"gap":false,"ele":2303.64,"speed":0.15,"hr":99.03,"cad":5.68,"temp":28.32},{"d":17.535,"t":29651,"gap":false,"ele":2308.17,"speed":0.0,"hr":90.45,"cad":0.0,"temp":27.68},{"d":17.56,"t":29789,"gap":false,"ele":2315.85,"speed":1.67,"hr":99.13,"cad":23.23,"temp":26.74},{"d":17.644,"t":29886,"gap":false,"ele":2318.71,"speed":2.38,"hr":118.39,"cad":4.94,"temp":27.0},{"d":17.66,"t":30025,"gap":false,"ele":2319.24,"speed":0.1,"hr":87.35,"cad":11.39,"temp":27.26},{"d":17.696,"t":30165,"gap":false,"ele":2315.7,"speed":0.76,"hr":86.45,"cad":7.84,"temp":28.0},{"d":17.782,"t":30288,"gap":false,"ele":2310.32,"speed":3.11,"hr":93.87,"cad":34.35,"temp":28.0},{"d":17.877,"t":30387,"gap":false,"ele":2305.04,"speed":3.68,"hr":94.19,"cad":27.42,"temp":27.94},{"d":17.943,"t":30472,"gap":false,"ele":2314.98,"speed":1.89,"hr":114.94,"cad":8.9,"temp":26.81},{"d":18.005,"t":30575,"gap":false,"ele":2327.05,"speed":0.0,"hr":119.39,"cad":0.0,"temp":26.39},{"d":18.033,"t":30671,"gap":false,"ele":2337.89,"speed":0.48,"hr":134.0,"cad":26.81,"temp":27.06},{"d":18.091,"t":30802,"gap":false,"ele":2343.49,"speed":0.77,"hr":103.71,"cad":0.0,"temp":26.03},{"d":18.154,"t":30919,"gap":false,"ele":2345.72,"speed":1.25,"hr":97.26,"cad":19.26,"temp":25.52},{"d":18.221,"t":31024,"gap":false,"ele":2356.88,"speed":0.62,"hr":111.74,"cad":14.06,"temp":25.0},{"d":18.292,"t":31129,"gap":false,"ele":2363.27,"speed":1.01,"hr":107.35,"cad":2.52,"temp":25.0},{"d":18.299,"t":31260,"gap":false,"ele":2371.13,"speed":0.0,"hr":106.32,"cad":0.0,"temp":25.0},{"d":18.299,"t":31399,"gap":false,"ele":2383.77,"speed":0.0,"hr":125.87,"cad":0.0,"temp":25.0},{"d":18.299,"t":31539,"gap":false,"ele":2392.5,"speed":0.0,"hr":112.87,"cad":0.0,"temp":24.35},{"d":18.382,"t":31657,"gap":false,"ele":2396.08,"speed":0.43,"hr":104.81,"cad":11.13,"temp":24.0},{"d":18.437,"t":31765,"gap":false,"ele":2406.97,"speed":0.0,"hr":114.45,"cad":0.0,"temp":24.0},{"d":18.457,"t":31881,"gap":false,"ele":2418.34,"speed":0.0,"hr":121.61,"cad":0.0,"temp":24.87},{"d":18.482,"t":32009,"gap":false,"ele":2429.74,"speed":0.03,"hr":121.1,"cad":0.0,"temp":25.0},{"d":18.519,"t":32124,"gap":false,"ele":2442.06,"speed":0.23,"hr":128.68,"cad":3.1,"temp":25.0},{"d":18.549,"t":32238,"gap":false,"ele":2452.17,"speed":0.0,"hr":118.84,"cad":0.0,"temp":25.45},{"d":18.573,"t":32362,"gap":false,"ele":2459.1,"speed":0.0,"hr":108.87,"cad":2.97,"temp":25.9},{"d":18.616,"t":32464,"gap":false,"ele":2471.14,"speed":0.88,"hr":132.97,"cad":5.42,"temp":26.77},{"d":18.629,"t":32599,"gap":false,"ele":2482.73,"speed":0.06,"hr":124.77,"cad":0.0,"temp":26.68},{"d":18.636,"t":32716,"gap":false,"ele":2492.93,"speed":0.0,"hr":123.03,"cad":0.0,"temp":24.84},{"d":18.636,"t":32868,"gap":false,"ele":2493.1,"speed":0.0,"hr":95.39,"cad":0.0,"temp":22.9},{"d":18.636,"t":33026,"gap":false,"ele":2491.08,"speed":0.0,"hr":84.97,"cad":0.0,"temp":21.74},{"d":18.681,"t":33131,"gap":false,"ele":2475.37,"speed":0.23,"hr":77.81,"cad":9.68,"temp":20.9},{"d":18.69,"t":33278,"gap":false,"ele":2474.5,"speed":0.0,"hr":80.06,"cad":3.29,"temp":20.77},{"d":18.719,"t":33421,"gap":false,"ele":2468.11,"speed":0.67,"hr":82.0,"cad":18.19,"temp":21.81},{"d":18.839,"t":33541,"gap":false,"ele":2465.32,"speed":3.21,"hr":80.19,"cad":32.52,"temp":22.06},{"d":18.913,"t":33626,"gap":false,"ele":2471.86,"speed":1.09,"hr":95.1,"cad":22.87,"temp":23.0},{"d":18.946,"t":33731,"gap":false,"ele":2481.0,"speed":0.0,"hr":122.71,"cad":7.77,"temp":23.0},{"d":18.98,"t":33848,"gap":false,"ele":2493.26,"speed":0.28,"hr":128.9,"cad":2.71,"temp":23.71},{"d":19.071,"t":33962,"gap":false,"ele":2506.4,"speed":0.0,"hr":136.45,"cad":2.61,"temp":24.74},{"d":19.184,"t":34087,"gap":false,"ele":2509.57,"speed":2.6,"hr":122.81,"cad":26.19,"temp":25.0},{"d":19.273,"t":34207,"gap":false,"ele":2509.55,"speed":1.38,"hr":125.81,"cad":20.84,"temp":25.0},{"d":19.313,"t":34342,"gap":false,"ele":2503.52,"speed":0.0,"hr":113.29,"cad":0.0,"temp":25.0},{"d":19.314,"t":34470,"gap":false,"ele":2500.57,"speed":0.0,"hr":90.45,"cad":0.0,"temp":26.0},{"d":19.315,"t":34643,"gap":false,"ele":2500.42,"speed":0.0,"hr":77.94,"cad":0.0,"temp":26.0},{"d":19.315,"t":34805,"gap":false,"ele":2500.46,"speed":0.0,"hr":78.87,"cad":0.0,"temp":26.0},{"d":19.348,"t":34936,"gap":false,"ele":2492.5,"speed":2.37,"hr":84.65,"cad":17.94,"temp":25.03},{"d":19.4,"t":35032,"gap":false,"ele":2476.14,"speed":1.12,"hr":72.32,"cad":4.58,"temp":24.1},{"d":19.466,"t":35121,"gap":false,"ele":2458.69,"speed":0.0,"hr":80.68,"cad":17.74,"temp":22.48},{"d":19.524,"t":35210,"gap":false,"ele":2442.08,"speed":1.15,"hr":89.39,"cad":6.81,"temp":21.45},{"d":19.593,"t":35279,"gap":false,"ele":2428.25,"speed":3.14,"hr":102.26,"cad":20.52,"temp":21.0},{"d":19.693,"t":35388,"gap":false,"ele":2424.85,"speed":2.67,"hr":98.9,"cad":17.06,"temp":20.13},{"d":19.798,"t":35474,"gap":false,"ele":2417.49,"speed":5.15,"hr":97.26,"cad":74.9,"temp":20.0},{"d":19.895,"t":35566,"gap":false,"ele":2411.76,"speed":1.7,"hr":105.77,"cad":36.35,"temp":20.0},{"d":19.996,"t":35663,"gap":false,"ele":2400.76,"speed":2.71,"hr":109.32,"cad":23.39,"temp":20.0},{"d":20.081,"t":35775,"gap":false,"ele":2395.23,"speed":0.95,"hr":113.42,"cad":27.26,"temp":20.68},{"d":20.149,"t":35867,"gap":false,"ele":2381.18,"speed":0.04,"hr":116.39,"cad":5.94,"temp":21.48},{"d":20.216,"t":35960,"gap":false,"ele":2359.35,"speed":0.25,"hr":119.03,"cad":10.71,"temp":22.84},{"d":20.319,"t":36063,"gap":false,"ele":2339.66,"speed":4.27,"hr":117.26,"cad":47.1,"temp":23.0},{"d":20.423,"t":36155,"gap":false,"ele":2327.8,"speed":3.33,"hr":116.42,"cad":31.26,"temp":23.87},{"d":20.513,"t":36266,"gap":false,"ele":2318.5,"speed":1.99,"hr":116.39,"cad":17.81,"temp":24.35},{"d":20.614,"t":36368,"gap":false,"ele":2310.22,"speed":3.83,"hr":120.77,"cad":46.52,"temp":25.0},{"d":20.708,"t":36501,"gap":false,"ele":2305.1,"speed":0.92,"hr":117.29,"cad":10.07,"temp":25.0}]}